odin_stream_cpp.abi3.so
odin_stream_cpp.pyi
odin_stream-0.1.4.dist-info/WHEEL
odin_stream-0.1.4.dist-info/RECORD
odin_stream-0.1.4.dist-info/METADATA
odin_stream-0.1.4.dist-info/licenses/LICENSE
lib/libparquet.so.1900
lib/libarrow.so.1900
lib/libarrow_substrait.so.1900
lib/libarrow_dataset.so.1900
lib/libarrow_acero.so.1900
lib/libarrow_python.so.1900
odin_stream/odin_db_mapping.py
odin_stream/odin_stream.py
odin_stream/__init__.py
