Metadata-Version: 2.1
Name: odin-stream
Version: 0.1.4
Summary: A libary to create datastreams of ODIN objects
Author-Email: Floris vernieuwe <floris@vernieuwe.eu>
License: MPL-2.0
Requires-Python: <4.0,>=3.10
Requires-Dist: nanobind>=2.6.1
Requires-Dist: polars>=1.27.1
Requires-Dist: pyarrow<20.0.0,>=19.0.0
Requires-Dist: scikit-build-core[pyproject]<0.11.0,>=0.10.7
Requires-Dist: nanobind<3.0.0,>=2.5.0
Requires-Dist: pytest<9.0.0,>=8.3.4
Requires-Dist: pytest-cov<7.0.0,>=6.0.0
Requires-Dist: pytest-benchmark<6.0.0,>=5.1.0
Requires-Dist: odin-db>=1.3.2
